<?xml version="1.0" encoding="UTF-8" standalone="no"?><root xmlns="http://www.javacore.ru/schemas/"><numberNeuronsFieldElem>3</numberNeuronsFieldElem><numberBinarySignsFieldElem>5</numberBinarySignsFieldElem><Images><Image id="0"><coef id="0">-1</coef><coef id="1">-1</coef><coef id="2">-1</coef><coef id="3">-1</coef><coef id="4">-1</coef><coef id="5">1</coef><coef id="6">1</coef><coef id="7">1</coef><coef id="8">1</coef><coef id="9">1</coef><coef id="10">-1</coef><coef id="11">-1</coef><coef id="12">1</coef><coef id="13">-1</coef><coef id="14">-1</coef><coef id="15">-1</coef><coef id="16">1</coef><coef id="17">-1</coef><coef id="18">1</coef><coef id="19">-1</coef><coef id="20">1</coef><coef id="21">-1</coef><coef id="22">-1</coef><coef id="23">-1</coef><coef id="24">1</coef></Image><Image id="1"><coef id="0">1</coef><coef id="1">-1</coef><coef id="2">-1</coef><coef id="3">-1</coef><coef id="4">-1</coef><coef id="5">1</coef><coef id="6">-1</coef><coef id="7">-1</coef><coef id="8">-1</coef><coef id="9">-1</coef><coef id="10">1</coef><coef id="11">1</coef><coef id="12">1</coef><coef id="13">1</coef><coef id="14">1</coef><coef id="15">1</coef><coef id="16">-1</coef><coef id="17">-1</coef><coef id="18">-1</coef><coef id="19">-1</coef><coef id="20">1</coef><coef id="21">-1</coef><coef id="22">-1</coef><coef id="23">-1</coef><coef id="24">-1</coef></Image><Image id="2"><coef id="0">1</coef><coef id="1">1</coef><coef id="2">1</coef><coef id="3">1</coef><coef id="4">1</coef><coef id="5">1</coef><coef id="6">-1</coef><coef id="7">-1</coef><coef id="8">-1</coef><coef id="9">-1</coef><coef id="10">1</coef><coef id="11">-1</coef><coef id="12">-1</coef><coef id="13">-1</coef><coef id="14">-1</coef><coef id="15">1</coef><coef id="16">-1</coef><coef id="17">-1</coef><coef id="18">-1</coef><coef id="19">-1</coef><coef id="20">1</coef><coef id="21">1</coef><coef id="22">1</coef><coef id="23">1</coef><coef id="24">1</coef></Image></Images></root>